<?xml version="1.0" encoding="utf-8"?>
<!-- This document provides minimal statistics about Fatal Crashes in
 the state of New Jersey as recorded by the New Jersey State Police.
 These statistics are unofficial and subject to change until the
 associated case is completed by the NJSP Fatal Accident
 Investigation Unit.-->
<FAUQSTATS>
  <RUNDATE>Sat Jan 18 10:00:05 EST 2025</RUNDATE>
  <STATSYEAR>2025</STATSYEAR>
  <COUNTY CCODE="01" CNAME="Atlantic">
  </COUNTY>
  <COUNTY CCODE="02" CNAME="Bergen">
  </COUNTY>
  <COUNTY CCODE="03" CNAME="Burlington">
  </COUNTY>
  <COUNTY CCODE="04" CNAME="Camden">
  </COUNTY>
  <COUNTY CCODE="05" CNAME="Cape May">
  </COUNTY>
  <COUNTY CCODE="06" CNAME="Cumberland">
  </COUNTY>
  <COUNTY CCODE="07" CNAME="Essex">
  </COUNTY>
  <COUNTY CCODE="08" CNAME="Gloucester">
  </COUNTY>
  <COUNTY CCODE="09" CNAME="Hudson">
  </COUNTY>
  <COUNTY CCODE="10" CNAME="Hunterdon">
  </COUNTY>
  <COUNTY CCODE="11" CNAME="Mercer">
  </COUNTY>
  <COUNTY CCODE="12" CNAME="Middlesex">
  </COUNTY>
  <COUNTY CCODE="13" CNAME="Monmouth">
  </COUNTY>
  <COUNTY CCODE="14" CNAME="Morris">
  </COUNTY>
  <COUNTY CCODE="15" CNAME="Ocean">
  </COUNTY>
  <COUNTY CCODE="16" CNAME="Passaic">
  </COUNTY>
  <COUNTY CCODE="17" CNAME="Salem">
  </COUNTY>
  <COUNTY CCODE="18" CNAME="Somerset">
  </COUNTY>
  <COUNTY CCODE="19" CNAME="Sussex">
  </COUNTY>
  <COUNTY CCODE="20" CNAME="Union">
  </COUNTY>
  <COUNTY CCODE="21" CNAME="Warren">
  </COUNTY>
  <COUNTY CCODE="04" CNAME="Camden">
    <MUNICIPALITY MCODE="0408" MNAME="Camden City">
      <ACCIDENT ACCID="13712" DATE="01/17/2025" TIME="1904">
        <STREET>2201 MOUNT EPHRAIM AVE CAMDEN CITY NJ 08104</STREET>
        <LOCATION>2201 MOUNT EPHRAIM AVE CAMDEN CITY NJ 08104</LOCATION>
        <FATALITIES>1</FATALITIES>
        <FATAL_D>0</FATAL_D>
        <FATAL_P>0</FATAL_P>
        <FATAL_T>1</FATAL_T>
        <FATAL_B>0</FATAL_B>
      </ACCIDENT>
    </MUNICIPALITY>
  </COUNTY>
  <COUNTY CCODE="03" CNAME="Burlington">
    <MUNICIPALITY MCODE="0315" MNAME="Florence Twsp">
      <ACCIDENT ACCID="13711" DATE="01/17/2025" TIME="0543">
        <STREET>Florence-Columbus Road (CR-656)</STREET>
        <LOCATION>Florence-Columbus Road (CR-656)</LOCATION>
        <FATALITIES>1</FATALITIES>
        <FATAL_D>0</FATAL_D>
        <FATAL_P>0</FATAL_P>
        <FATAL_T>1</FATAL_T>
        <FATAL_B>0</FATAL_B>
      </ACCIDENT>
    </MUNICIPALITY>
  </COUNTY>
  <COUNTY CCODE="02" CNAME="Bergen">
    <MUNICIPALITY MCODE="0233" MNAME="Mahwah Twsp">
      <ACCIDENT ACCID="13710" DATE="01/16/2025" TIME="1742">
        <HIGHWAY>287</HIGHWAY>
        <LOCATION>Interstate 287</LOCATION>
        <FATALITIES>1</FATALITIES>
        <FATAL_D>1</FATAL_D>
        <FATAL_P>0</FATAL_P>
        <FATAL_T>0</FATAL_T>
        <FATAL_B>0</FATAL_B>
      </ACCIDENT>
    </MUNICIPALITY>
  </COUNTY>
  <COUNTY CCODE="17" CNAME="Salem">
    <MUNICIPALITY MCODE="1710" MNAME="Pittsgrove Twsp">
      <ACCIDENT ACCID="13706" DATE="01/15/2025" TIME="2145">
        <HIGHWAY>40</HIGHWAY>
        <LOCATION>State Highway 40 MP 21.8</LOCATION>
        <FATALITIES>1</FATALITIES>
        <FATAL_D>1</FATAL_D>
        <FATAL_P>0</FATAL_P>
        <FATAL_T>0</FATAL_T>
        <FATAL_B>0</FATAL_B>
        <INJURIES>1</INJURIES>
      </ACCIDENT>
    </MUNICIPALITY>
  </COUNTY>
  <COUNTY CCODE="01" CNAME="Atlantic">
    <MUNICIPALITY MCODE="0111" MNAME="Galloway Twsp">
      <ACCIDENT ACCID="13705" DATE="01/15/2025" TIME="1523">
        <HIGHWAY>634</HIGHWAY>
        <LOCATION>County 634</LOCATION>
        <FATALITIES>1</FATALITIES>
        <FATAL_D>1</FATAL_D>
        <FATAL_P>0</FATAL_P>
        <FATAL_T>0</FATAL_T>
        <FATAL_B>0</FATAL_B>
      </ACCIDENT>
    </MUNICIPALITY>
  </COUNTY>
  <COUNTY CCODE="05" CNAME="Cape May">
    <MUNICIPALITY MCODE="0505" MNAME="Lower Twsp">
      <ACCIDENT ACCID="13704" DATE="01/14/2025" TIME="1134">
        <HIGHWAY>603</HIGHWAY>
        <LOCATION>County 603 MP 5.56</LOCATION>
        <FATALITIES>1</FATALITIES>
        <FATAL_D>1</FATAL_D>
        <FATAL_P>0</FATAL_P>
        <FATAL_T>0</FATAL_T>
        <FATAL_B>0</FATAL_B>
      </ACCIDENT>
    </MUNICIPALITY>
  </COUNTY>
  <COUNTY CCODE="15" CNAME="Ocean">
    <MUNICIPALITY MCODE="1506" MNAME="Brick Twsp">
      <ACCIDENT ACCID="13701" DATE="01/13/2025" TIME="1037">
        <HIGHWAY>88</HIGHWAY>
        <LOCATION>State Highway 88</LOCATION>
        <FATALITIES>1</FATALITIES>
        <FATAL_D>1</FATAL_D>
        <FATAL_P>0</FATAL_P>
        <FATAL_T>0</FATAL_T>
        <FATAL_B>0</FATAL_B>
      </ACCIDENT>
    </MUNICIPALITY>
    <MUNICIPALITY MCODE="1507" MNAME="Toms River">
      <ACCIDENT ACCID="13703" DATE="01/12/2025" TIME="1743">
        <HIGHWAY>166</HIGHWAY>
        <LOCATION>State Highway 166 MP 2.7</LOCATION>
        <FATALITIES>1</FATALITIES>
        <FATAL_D>0</FATAL_D>
        <FATAL_P>0</FATAL_P>
        <FATAL_T>1</FATAL_T>
        <FATAL_B>0</FATAL_B>
        <INJURIES>0</INJURIES>
      </ACCIDENT>
    </MUNICIPALITY>
  </COUNTY>
  <COUNTY CCODE="04" CNAME="Camden">
    <MUNICIPALITY MCODE="0408" MNAME="Camden City">
      <ACCIDENT ACCID="13697" DATE="01/12/2025" TIME="0933">
        <HIGHWAY>30</HIGHWAY>
        <LOCATION>State Highway 30</LOCATION>
        <FATALITIES>1</FATALITIES>
        <FATAL_D>1</FATAL_D>
        <FATAL_P>0</FATAL_P>
        <FATAL_T>0</FATAL_T>
        <FATAL_B>0</FATAL_B>
      </ACCIDENT>
    </MUNICIPALITY>
  </COUNTY>
  <COUNTY CCODE="01" CNAME="Atlantic">
    <MUNICIPALITY MCODE="0112" MNAME="Hamilton Twsp">
      <ACCIDENT ACCID="13699" DATE="01/12/2025" TIME="0509">
        <HIGHWAY>446</HIGHWAY>
        <LOCATION>Atlantic City Expressway MP 13.2</LOCATION>
        <FATALITIES>1</FATALITIES>
        <FATAL_D>0</FATAL_D>
        <FATAL_P>0</FATAL_P>
        <FATAL_T>1</FATAL_T>
        <FATAL_B>0</FATAL_B>
      </ACCIDENT>
    </MUNICIPALITY>
  </COUNTY>
  <COUNTY CCODE="12" CNAME="Middlesex">
    <MUNICIPALITY MCODE="1201" MNAME="Carteret Boro">
      <ACCIDENT ACCID="13700" DATE="01/11/2025" TIME="2154">
        <HIGHWAY>602</HIGHWAY>
        <LOCATION>County 602</LOCATION>
        <FATALITIES>1</FATALITIES>
        <FATAL_D>1</FATAL_D>
        <FATAL_P>0</FATAL_P>
        <FATAL_T>0</FATAL_T>
        <FATAL_B>0</FATAL_B>
      </ACCIDENT>
    </MUNICIPALITY>
  </COUNTY>
  <COUNTY CCODE="04" CNAME="Camden">
    <MUNICIPALITY MCODE="0427" MNAME="Pennsauken Twsp">
      <ACCIDENT ACCID="13696" DATE="01/11/2025" TIME="1357">
        <HIGHWAY>90</HIGHWAY>
        <LOCATION>State Highway 90</LOCATION>
        <FATALITIES>1</FATALITIES>
        <FATAL_D>1</FATAL_D>
        <FATAL_P>0</FATAL_P>
        <FATAL_T>0</FATAL_T>
        <FATAL_B>0</FATAL_B>
      </ACCIDENT>
    </MUNICIPALITY>
  </COUNTY>
  <COUNTY CCODE="20" CNAME="Union">
    <MUNICIPALITY MCODE="2004" MNAME="Elizabeth City">
      <ACCIDENT ACCID="13695" DATE="01/09/2025" TIME="2246">
        <HIGHWAY>629</HIGHWAY>
        <LOCATION>County 629</LOCATION>
        <FATALITIES>1</FATALITIES>
        <FATAL_D>0</FATAL_D>
        <FATAL_P>0</FATAL_P>
        <FATAL_T>1</FATAL_T>
        <FATAL_B>0</FATAL_B>
      </ACCIDENT>
    </MUNICIPALITY>
  </COUNTY>
  <COUNTY CCODE="04" CNAME="Camden">
    <MUNICIPALITY MCODE="0408" MNAME="Camden City">
      <ACCIDENT ACCID="13702" DATE="01/09/2025" TIME="1530">
        <STREET>Atlantic Ave</STREET>
        <LOCATION>Atlantic Ave</LOCATION>
        <FATALITIES>1</FATALITIES>
        <FATAL_D>1</FATAL_D>
        <FATAL_P>0</FATAL_P>
        <FATAL_T>0</FATAL_T>
        <FATAL_B>0</FATAL_B>
      </ACCIDENT>
    </MUNICIPALITY>
    <MUNICIPALITY MCODE="0416" MNAME="Haddon Twsp">
      <ACCIDENT ACCID="13691" DATE="01/07/2025" TIME="0638">
        <HIGHWAY>130</HIGHWAY>
        <LOCATION>State Highway 130</LOCATION>
        <FATALITIES>1</FATALITIES>
        <FATAL_D>1</FATAL_D>
        <FATAL_P>0</FATAL_P>
        <FATAL_T>0</FATAL_T>
        <FATAL_B>0</FATAL_B>
      </ACCIDENT>
    </MUNICIPALITY>
  </COUNTY>
  <COUNTY CCODE="12" CNAME="Middlesex">
    <MUNICIPALITY MCODE="1209" MNAME="Old Bridge Twsp">
      <ACCIDENT ACCID="13694" DATE="01/04/2025" TIME="0956">
        <HIGHWAY>444</HIGHWAY>
        <LOCATION>Garden State Parkway MP 122.2</LOCATION>
        <FATALITIES>1</FATALITIES>
        <FATAL_D>1</FATAL_D>
        <FATAL_P>0</FATAL_P>
        <FATAL_T>0</FATAL_T>
        <FATAL_B>0</FATAL_B>
        <INJURIES>0</INJURIES>
      </ACCIDENT>
    </MUNICIPALITY>
  </COUNTY>
  <COUNTY CCODE="11" CNAME="Mercer">
    <MUNICIPALITY MCODE="1103" MNAME="Hamilton Twsp">
      <ACCIDENT ACCID="13686" DATE="01/02/2025" TIME="2201">
        <HIGHWAY>95</HIGHWAY>
        <LOCATION>New Jersey Turnpike MP 59.2</LOCATION>
        <FATALITIES>1</FATALITIES>
        <FATAL_D>0</FATAL_D>
        <FATAL_P>0</FATAL_P>
        <FATAL_T>1</FATAL_T>
        <FATAL_B>0</FATAL_B>
      </ACCIDENT>
    </MUNICIPALITY>
  </COUNTY>
  <COUNTY CCODE="12" CNAME="Middlesex">
    <MUNICIPALITY MCODE="1221" MNAME="South Brunswick Tws">
      <ACCIDENT ACCID="13682" DATE="01/01/2025" TIME="0724">
        <HIGHWAY>130</HIGHWAY>
        <LOCATION>State Highway 130</LOCATION>
        <FATALITIES>1</FATALITIES>
        <FATAL_D>0</FATAL_D>
        <FATAL_P>1</FATAL_P>
        <FATAL_T>0</FATAL_T>
        <FATAL_B>0</FATAL_B>
      </ACCIDENT>
    </MUNICIPALITY>
  </COUNTY>
  <TOTACCIDENTS>18</TOTACCIDENTS>
  <TOTFATALITIES>18</TOTFATALITIES>
  <TOTINJURIES>1</TOTINJURIES>
</FAUQSTATS>
